[
  {
    "title": "Front End Web Developer | 痞客邦",
    "des": "2018 / 07 - 2020 / 03"
  },
  {
    "title": "Front End Web Developer | 三竹資訊",
    "des": "2015 / 02 - 2018 / 07"
  },
  {
    "title": "ALPHA Hackathon",
    "des": "2015 / 01"
  },
  {
    "title": "Front End Web Developer | 春樹科技",
    "des": "2014 / 07 - 2015 / 01"
  },
  {
    "title": "Front End Web Developer | Uni-Net 聯網國際",
    "des": "2013 / 09 - 2014 / 07"
  },
  {
    "title": "Web Designer | TutorABC",
    "des": "2012 / 06 - 2013 / 06"
  }
]
